rawpipe/__init__.py
rawpipe/rawpipe.py
rawpipe/version.py
test/__init__.py
test/regression.py
rawpipe-0.19.0.dist-info/LICENSE
rawpipe-0.19.0.dist-info/METADATA
rawpipe-0.19.0.dist-info/WHEEL
rawpipe-0.19.0.dist-info/top_level.txt
rawpipe-0.19.0.dist-info/zip-safe
rawpipe-0.19.0.dist-info/RECORD
