Metadata-Version: 2.1
Name: rawpipe
Version: 0.19.0
Summary: A collection of camera raw processing algorithms.
Home-page: http://github.com/toaarnio/rawpipe
Author: Tomi Aarnio
Author-email: tomi.p.aarnio@gmail.com
License: MIT
Platform: UNKNOWN
License-File: LICENSE
Requires-Dist: numpy (>=1.21.0)
Requires-Dist: opencv-python-headless (>=4.5.0)
